optobot/__init__.py
optobot/automate.py
optobot/ot2_protocol.py
optobot/colorimetric/__init__.py
optobot/colorimetric/colours.py
optobot/colorimetric/image_capture/__init__.py
optobot/colorimetric/image_capture/photo.py
optobot/colorimetric/image_capture/photo_crop.py
optobot/colorimetric/image_processing/__init__.py
optobot/colorimetric/image_processing/contours.py
optobot/colorimetric/image_processing/contours_adapted.py
optobot/colorimetric/image_processing/extrapolated_grid.py
optobot/colorimetric/image_processing/fixed_grid.py
optobot/optimisation/__init__.py
optobot/optimisation/optimisers.py
optobot-0.1.2.dist-info/licenses/LICENSE
optobot-0.1.2.dist-info/METADATA
optobot-0.1.2.dist-info/WHEEL
optobot-0.1.2.dist-info/top_level.txt
optobot-0.1.2.dist-info/RECORD
