Metadata-Version: 2.4
Name: optobot
Version: 0.1.2
Summary: A package for automated experimental optimisation using an Opentrons OT-2 robot.
Author: Akthar Uzzaman, Hanxuan Sheng, Hodan Abdi, Nicola Egues Muhlberger, Pavan Ponupureddi, Sebastian Parkin
License-Expression: MIT
Project-URL: Homepage, https://github.com/nicolaegues/OptoBot
Project-URL: Documentation, https://optobot.readthedocs.io/en/latest/
Classifier: Operating System :: OS Independent
Classifier: Programming Language :: Python :: 3.10
Classifier: Programming Language :: Python :: 3.11
Classifier: Programming Language :: Python :: 3.12
Classifier: Development Status :: 3 - Alpha
Classifier: Intended Audience :: Science/Research
Classifier: Intended Audience :: Education
Classifier: Intended Audience :: Developers
Classifier: Topic :: Scientific/Engineering
Classifier: Topic :: Scientific/Engineering :: Chemistry
Requires-Python: <3.13,>=3.10
License-File: LICENSE
Requires-Dist: matplotlib==3.9.2
Requires-Dist: numpy==1.26.4
Requires-Dist: opencv-python==4.11.0.86
Requires-Dist: opentrons==8.3.0
Requires-Dist: pandas==2.2.3
Requires-Dist: pyswarms==1.3.0
Requires-Dist: scikit-optimize==0.10.2
Dynamic: license-file
